shpextractor/__init__.py
shpextractor/shpextractor.py
shpextractor-0.1.0.dist-info/METADATA
shpextractor-0.1.0.dist-info/WHEEL
shpextractor-0.1.0.dist-info/top_level.txt
shpextractor-0.1.0.dist-info/RECORD
